{"page":1,"rp":50,"total":12740,"url":"http://taginfo.openstreetmap.org/api/4/key/values?key=length&page=1&rp=50&sortname=count&sortorder=desc","data":[{"value":"0.159","count":199,"fraction":0.0024000000000000002,"in_wiki":false,"description":""},{"value":"0.13","count":196,"fraction":0.0024000000000000002,"in_wiki":false,"description":""},{"value":"0.146","count":194,"fraction":0.0023,"in_wiki":false,"description":""},{"value":"0.143","count":192,"fraction":0.0023,"in_wiki":false,"description":""},{"value":"0.131","count":191,"fraction":0.0023,"in_wiki":false,"description":""},{"value":"0.155","count":191,"fraction":0.0023,"in_wiki":false,"description":""},{"value":"0.167","count":191,"fraction":0.0023,"in_wiki":false,"description":""},{"value":"0.148","count":189,"fraction":0.0023,"in_wiki":false,"description":""},{"value":"0.177","count":189,"fraction":0.0023,"in_wiki":false,"description":""},{"value":"0.133","count":188,"fraction":0.0023,"in_wiki":false,"description":""},{"value":"0.144","count":188,"fraction":0.0023,"in_wiki":false,"description":""},{"value":"0.156","count":188,"fraction":0.0023,"in_wiki":false,"description":""},{"value":"0.161","count":186,"fraction":0.0022,"in_wiki":false,"description":""},{"value":"0.166","count":186,"fraction":0.0022,"in_wiki":false,"description":""},{"value":"0.162","count":185,"fraction":0.0022,"in_wiki":false,"description":""},{"value":"0.139","count":183,"fraction":0.0022,"in_wiki":false,"description":""},{"value":"0.15","count":183,"fraction":0.0022,"in_wiki":false,"description":""},{"value":"0.154","count":182,"fraction":0.0022,"in_wiki":false,"description":""},{"value":"0.113","count":181,"fraction":0.0022,"in_wiki":false,"description":""},{"value":"0.129","count":181,"fraction":0.0022,"in_wiki":false,"description":""},{"value":"0.157","count":181,"fraction":0.0022,"in_wiki":false,"description":""},{"value":"0.168","count":181,"fraction":0.0022,"in_wiki":false,"description":""},{"value":"0.188","count":181,"fraction":0.0022,"in_wiki":false,"description":""},{"value":"0.145","count":180,"fraction":0.0022,"in_wiki":false,"description":""},{"value":"0.151","count":180,"fraction":0.0022,"in_wiki":false,"description":""},{"value":"0.178","count":179,"fraction":0.0022,"in_wiki":false,"description":""},{"value":"0.116","count":178,"fraction":0.0021000000000000003,"in_wiki":false,"description":""},{"value":"0.135","count":177,"fraction":0.0021000000000000003,"in_wiki":false,"description":""},{"value":"0.176","count":177,"fraction":0.0021000000000000003,"in_wiki":false,"description":""},{"value":"0.17","count":177,"fraction":0.0021000000000000003,"in_wiki":false,"description":""},{"value":"0.102","count":176,"fraction":0.0021000000000000003,"in_wiki":false,"description":""},{"value":"0.136","count":176,"fraction":0.0021000000000000003,"in_wiki":false,"description":""},{"value":"0.125","count":175,"fraction":0.0021000000000000003,"in_wiki":false,"description":""},{"value":"0.104","count":174,"fraction":0.0021000000000000003,"in_wiki":false,"description":""},{"value":"0.122","count":174,"fraction":0.0021000000000000003,"in_wiki":false,"description":""},{"value":"0.158","count":173,"fraction":0.0021000000000000003,"in_wiki":false,"description":""},{"value":"0.142","count":172,"fraction":0.0021000000000000003,"in_wiki":false,"description":""},{"value":"0.152","count":172,"fraction":0.0021000000000000003,"in_wiki":false,"description":""},{"value":"0.209","count":172,"fraction":0.0021000000000000003,"in_wiki":false,"description":""},{"value":"0.115","count":171,"fraction":0.0021000000000000003,"in_wiki":false,"description":""},{"value":"0.153","count":171,"fraction":0.0021000000000000003,"in_wiki":false,"description":""},{"value":"0.198","count":171,"fraction":0.0021000000000000003,"in_wiki":false,"description":""},{"value":"0.179","count":170,"fraction":0.002,"in_wiki":false,"description":""},{"value":"0.185","count":170,"fraction":0.002,"in_wiki":false,"description":""},{"value":"0.187","count":170,"fraction":0.002,"in_wiki":false,"description":""},{"value":"0.118","count":169,"fraction":0.002,"in_wiki":false,"description":""},{"value":"0.134","count":169,"fraction":0.002,"in_wiki":false,"description":""},{"value":"0.163","count":169,"fraction":0.002,"in_wiki":false,"description":""},{"value":"0.184","count":169,"fraction":0.002,"in_wiki":false,"description":""},{"value":"0.11","count":169,"fraction":0.002,"in_wiki":false,"description":""}]}